cdk8s_utils/__init__.py
cdk8s_utils/cli.py
cdk8s_utils-0.1.1.dist-info/METADATA
cdk8s_utils-0.1.1.dist-info/WHEEL
cdk8s_utils-0.1.1.dist-info/top_level.txt
cdk8s_utils-0.1.1.dist-info/RECORD
